<?xml version="1.0" ?>
<annotation>
	<videoname>Python Tutorial for Beginners 16 - Class Constructors (_init_) and Destructor  (_del_)</videoname>
	<box>
		<pos>00562</pos>
	</box>
	<bndbox>
		<xmin>1240</xmin>
		<ymin>245</ymin>
		<xmax>1249</xmax>
		<ymax>302</ymax>
	</bndbox>
	<bndbox>
		<xmin>1175</xmin>
		<ymin>269</ymin>
		<xmax>1199</xmax>
		<ymax>302</ymax>
	</bndbox>
	<bndbox>
		<xmin>1010</xmin>
		<ymin>264</ymin>
		<xmax>1035</xmax>
		<ymax>298</ymax>
	</bndbox>
	<bndbox>
		<xmin>1096</xmin>
		<ymin>158</ymin>
		<xmax>1106</xmax>
		<ymax>206</ymax>
	</bndbox>
	<max_box>
		<xmin>1010</xmin>
		<ymin>264</ymin>
		<xmax>1035</xmax>
		<ymax>298</ymax>
	</max_box>
	<max_region>
		<xmin>1010</xmin>
		<ymin>158</ymin>
		<xmax>1249</xmax>
		<ymax>302</ymax>
	</max_region>
</annotation>
