<?xml version="1.0" ?>
<annotation>
	<videoname>Python Tutorial for Beginners 16 - Class Constructors (_init_) and Destructor  (_del_)</videoname>
	<box>
		<pos>00573</pos>
	</box>
	<bndbox>
		<xmin>1275</xmin>
		<ymin>258</ymin>
		<xmax>1451</xmax>
		<ymax>346</ymax>
	</bndbox>
	<bndbox>
		<xmin>1548</xmin>
		<ymin>295</ymin>
		<xmax>1599</xmax>
		<ymax>333</ymax>
	</bndbox>
	<bndbox>
		<xmin>1827</xmin>
		<ymin>297</ymin>
		<xmax>1885</xmax>
		<ymax>333</ymax>
	</bndbox>
	<bndbox>
		<xmin>1484</xmin>
		<ymin>295</ymin>
		<xmax>1541</xmax>
		<ymax>326</ymax>
	</bndbox>
	<bndbox>
		<xmin>1602</xmin>
		<ymin>295</ymin>
		<xmax>1760</xmax>
		<ymax>326</ymax>
	</bndbox>
	<bndbox>
		<xmin>1760</xmin>
		<ymin>295</ymin>
		<xmax>1789</xmax>
		<ymax>326</ymax>
	</bndbox>
	<bndbox>
		<xmin>1792</xmin>
		<ymin>297</ymin>
		<xmax>1834</xmax>
		<ymax>326</ymax>
	</bndbox>
	<bndbox>
		<xmin>1452</xmin>
		<ymin>302</ymin>
		<xmax>1464</xmax>
		<ymax>326</ymax>
	</bndbox>
	<max_box>
		<xmin>1275</xmin>
		<ymin>258</ymin>
		<xmax>1451</xmax>
		<ymax>346</ymax>
	</max_box>
	<max_region>
		<xmin>1275</xmin>
		<ymin>258</ymin>
		<xmax>1885</xmax>
		<ymax>346</ymax>
	</max_region>
</annotation>
